catenaconf/__init__.py
catenaconf/ops.py
catenaconf/catena_config/__init__.py
catenaconf/catena_config/kvconfig.py
tests/__init__.py
tests/test.py
tests/test_config.py
catenaconf-0.1.4.dist-info/LICENSE
catenaconf-0.1.4.dist-info/METADATA
catenaconf-0.1.4.dist-info/WHEEL
catenaconf-0.1.4.dist-info/top_level.txt
catenaconf-0.1.4.dist-info/RECORD
