Metadata-Version: 2.1
Name: catenaconf
Version: 0.1.4
Summary: A configuration management library
Home-page: https://github.com/Asianfleet/catenaconf
Author: Jianqing Wang
Author-email: Jianqing Wang <18353419066@163.com>
Project-URL: Source, https://github.com/Asianfleet/catenaconf
Classifier: Programming Language :: Python :: 3.6
Classifier: Programming Language :: Python :: 3.7
Classifier: Programming Language :: Python :: 3.8
Classifier: Programming Language :: Python :: 3.9
Classifier: Programming Language :: Python :: 3.10
Classifier: Programming Language :: Python :: 3.11
Classifier: Programming Language :: Python :: 3.12
Classifier: Programming Language :: Python :: 3.13
Classifier: License :: OSI Approved :: MIT License
Classifier: Operating System :: OS Independent
Requires-Python: >=3.6
License-File: LICENSE
